pyejs/__init__.py
pyejs/pyejs.py
pyejs/utils.py
pyejs-0.1.0.dist-info/licenses/LICENSE
pyejs-0.1.0.dist-info/METADATA
pyejs-0.1.0.dist-info/WHEEL
pyejs-0.1.0.dist-info/top_level.txt
pyejs-0.1.0.dist-info/RECORD
