Metadata-Version: 2.4
Name: pyejs
Version: 0.1.0
Summary: A Python template engine inspired by EJS for dynamic HTML rendering.
Home-page: https://github.com/SanjhDeySarker/pyejs.git
Author: Sanjh
Author-email: sanjhdeysarker@gmail.com
License: MIT
Classifier: Programming Language :: Python :: 3
Classifier: License :: OSI Approved :: MIT License
Classifier: Operating System :: OS Independent
Classifier: Topic :: Text Processing :: Markup :: HTML
Requires-Python: >=3.8
License-File: LICENSE
Dynamic: author
Dynamic: author-email
Dynamic: classifier
Dynamic: description
Dynamic: description-content-type
Dynamic: home-page
Dynamic: license
Dynamic: license-file
Dynamic: requires-python
Dynamic: summary
